cfgtree/README.rst
cfgtree/__init__.py
cfgtree/cfgtree.py
cfgtree/dictxpath.py
cfgtree/storages.py
cfgtree/types.py
cfgtree/tests/__init__.py
cfgtree/tests/test_dictxparth.py
dopplerr/__init__.py
dopplerr/config.py
dopplerr/db.py
dopplerr/downloader.py
dopplerr/json.py
dopplerr/logging.py
dopplerr/main.py
dopplerr/main_pyannotate.py
dopplerr/request_filter.py
dopplerr/response.py
dopplerr/routes.py
dopplerr/singleton.py
dopplerr/status.py
dopplerr/api/__init__.py
dopplerr/api/v1/__init__.py
dopplerr/api/v1/config.py
dopplerr/api/v1/events.py
dopplerr/api/v1/medias.py
dopplerr/api/v1/notify.py
dopplerr/api/v1/series.py
dopplerr/api/v1/status.py
dopplerr/descriptors/__init__.py
dopplerr/descriptors/media_types.py
dopplerr/descriptors/series.py
dopplerr/notifications/__init__.py
dopplerr/notifications/_base.py
dopplerr/notifications/pushover.py
dopplerr/notifications_types/__init__.py
dopplerr/notifications_types/_base.py
dopplerr/notifications_types/series_media_refreshed.py
dopplerr/notifications_types/series_subtitles_fetched.py
dopplerr/plugins/__init__.py
dopplerr/plugins/sonarr/__init__.py
dopplerr/plugins/sonarr/filter.py
dopplerr/plugins/sonarr/response.py
dopplerr/plugins/sonarr/task.py
dopplerr/tasks/__init__.py
dopplerr/tasks/base.py
dopplerr/tasks/disk_scanner.py
dopplerr/tasks/download_subtitles.py
dopplerr/tasks/manager.py
dopplerr/tasks/periodic.py
dopplerr/tasks/queued.py
dopplerr/tasks/threaded.py
dopplerr/tasks/subtasks/__init__.py
dopplerr/tasks/subtasks/subliminal.py
dopplerr/tasks/tests/__init__.py
dopplerr/tasks/tests/test_aps.py
dopplerr/tasks/tests/test_download_subtitles.py
dopplerr/tasks/tests/test_executors.py
dopplerr/tasks/tests/test_queued.py
dopplerr/tests/__init__.py
dopplerr-0.6.4.dist-info/DESCRIPTION.rst
dopplerr-0.6.4.dist-info/METADATA
dopplerr-0.6.4.dist-info/RECORD
dopplerr-0.6.4.dist-info/WHEEL
dopplerr-0.6.4.dist-info/entry_points.txt
dopplerr-0.6.4.dist-info/metadata.json
dopplerr-0.6.4.dist-info/pbr.json
dopplerr-0.6.4.dist-info/top_level.txt
