Metadata-Version: 2.0
Name: dopplerr
Version: 0.6.4
Summary: Subtitle Download Web Service for Sonarr
Home-page: https://github.com/Stibbons/dopplerr
Author: Gaetan Semet
Author-email: gaetan@xeberon.net
License: UNKNOWN
Platform: UNKNOWN
Classifier: Intended Audience :: Information Technology
Classifier: Intended Audience :: System Administrators
Classifier: License :: OSI Approved :: MIT License
Classifier: Operating System :: POSIX :: Linux
Classifier: Programming Language :: Python
Classifier: Programming Language :: Python :: 3.6
Classifier: Topic :: Multimedia :: Video
Requires-Dist: aiofiles
Requires-Dist: aiohttp
Requires-Dist: apscheduler
Requires-Dist: apsw
Requires-Dist: colorlog
Requires-Dist: pbr
Requires-Dist: peewee
Requires-Dist: sanic
Requires-Dist: sanic-transmute
Requires-Dist: setuptools (!=36.0.0)
Requires-Dist: subliminal
